wellpathpy/__init__.py
wellpathpy/checkarrays.py
wellpathpy/geometry.py
wellpathpy/header.py
wellpathpy/location.py
wellpathpy/mincurve.py
wellpathpy/position_log.py
wellpathpy/rad_curv.py
wellpathpy/read.py
wellpathpy/tan.py
wellpathpy/write.py
wellpathpy/test/__init__.py
wellpathpy/test/test_ave_tan.py
wellpathpy/test/test_bal_tan.py
wellpathpy/test/test_calculations.py
wellpathpy/test/test_core.py
wellpathpy/test/test_geometry.py
wellpathpy/test/test_header.py
wellpathpy/test/test_high_tan.py
wellpathpy/test/test_location.py
wellpathpy/test/test_low_tan.py
wellpathpy/test/test_mincurve.py
wellpathpy/test/test_position_log.py
wellpathpy/test/test_rad_curve.py
wellpathpy/test/test_read.py
wellpathpy/test/test_workflow.py
wellpathpy/test/test_write.py
wellpathpy/test/fixtures/Well_Surveys_Projected_to_TD.csv
wellpathpy/test/fixtures/header.json
wellpathpy/test/fixtures/mock_data_set.csv
wellpathpy/test/fixtures/straight_dev_section.csv
wellpathpy/test/fixtures/straight_vert_section.csv
wellpathpy/test/fixtures/well10.csv
wellpathpy/test/fixtures/well9.csv
wellpathpy-0.5.1.dist-info/METADATA
wellpathpy-0.5.1.dist-info/WHEEL
wellpathpy-0.5.1.dist-info/licenses/LICENSE
wellpathpy-0.5.1.dist-info/RECORD
