Metadata-Version: 2.3
Name: wellpathpy
Version: 0.5.1
Summary: Light package to load well deviations
Project-URL: Homepage, https://github.com/Zabamund/wellpathpy
Project-URL: Repository, https://github.com/Zabamund/wellpathpy
Author-email: Robert Leckenby <fracgeol@gmail.com>, Jørgen Kvalsvik <j@lambda.is>, Brendon Hall <brendon.hall@gmail.com>
License:                    GNU LESSER GENERAL PUBLIC LICENSE
Requires-Dist: numpy>=1.10
Provides-Extra: test
Requires-Dist: hypothesis; extra == 'test'
Requires-Dist: pytest; extra == 'test'
